<?xml version="1.0" encoding="UTF-8"?>
<objects serializationModel="Studio.01.10.00">
    <object class="AudioFile" id="{6b55a66e-dd9e-4083-9dd8-5a755376cba2}">
        <property name="assetPath">
            <value>SoundFX_01.wav</value>
        </property>
        <property name="frequencyInKHz">
            <value>44.0999985</value>
        </property>
        <property name="channelCount">
            <value>2</value>
        </property>
        <property name="length">
            <value>3.7366213151927439</value>
        </property>
        <relationship name="masterAssetFolder">
            <destination>{2414e6ec-8bd6-4ccb-88e4-bdb7a325a63b}</destination>
        </relationship>
    </object>
</objects>
