<?xml version="1.0" encoding="UTF-8"?>
<objects serializationModel="Studio.01.10.00">
    <object class="AudioFile" id="{e97d162e-645c-49df-992a-5fd5809262f3}">
        <property name="assetPath">
            <value>SoundFX_03.wav</value>
        </property>
        <property name="frequencyInKHz">
            <value>44.0999985</value>
        </property>
        <property name="channelCount">
            <value>2</value>
        </property>
        <property name="length">
            <value>3.8191836734693876</value>
        </property>
        <relationship name="masterAssetFolder">
            <destination>{2414e6ec-8bd6-4ccb-88e4-bdb7a325a63b}</destination>
        </relationship>
    </object>
</objects>
